Workbook

Sheet Summary Cap
A1: SavetheWhales
A3: Pro Forma Series A Financing Calculator
D4: $3M Pre-Money | E4: $3.5M Pre-Money | F4: $4M Pre-Money | G4: $4.5M Pre-Money | H4: $5M Pre-Money | I4: $5.5M Pre-Money | J4: $6M Pre-Money
A5: Series A Price | B5: 0.47671876 | D5: 0.17671875 | E5: 0.22671875 | F5: 0.27671875 | G5: 0.32671876 | H5: 0.37671875 | I5: 0.42671874 | J5: 0.47671876
A6: Amount Raised | B6: =B33 -> 3000000.2
A7: Pre-Money Valuation | B7: =ROUND((B5*(I18+B28)),2) -> 6000000
A8: Post-Closing Valuation | B8: =ROUND((B5*I28),2) -> 10931250
A9: Target Post Closing Option Pool | B9: 0.2
B12: Pre Series A Preferred Stock Financing/Post Common Recap
B13: Base Conversion Price | C13: Current Conversion Price | D13: Current Conversion Ratio | E13: Shares Outstanding | F13: Options Outstanding | G13: Warrants Outstanding | H13: Total Outstanding | I13: Total Common Equiv. O/S | J13: Percentage | K13: Remaining Option Pool | L13: Fully Diluted Percentage
A14: Common | D14: 1 | E14: ='Common Stock'!B30 -> 7000000 | F14: ='2015 Option Plan'!B4 -> 0 | G14: 0 | H14: =E14+F14+G14 -> 7000000 | I14: =ROUND((H14*D14),0) -> 7000000 | J14: =I14/I16 -> 0.875 | K14: ='2015 Option Plan'!B8 -> 2000000 | L14: =I14/($I$18) -> 0.7
A15: Series FF Preferred Stock | B15: 0.01 | C15: 0.01 | D15: =B15/C15 -> 1 | E15: ='FF Preferred'!B12 -> 1000000 | F15: 0 | G15: 0 | H15: =E15+F15+G15 -> 1000000 | I15: =ROUND((H15*D15),0) -> 1000000 | J15: =I15/I16 -> 0.125 | L15: =I15/($I$18) -> 0.1
A16: Total | E16: =SUM(E14:E15) -> 8000000 | F16: =SUM(F14:F14) -> 0 | G16: =SUM(G14:G14) -> 0 | H16: =SUM(H14:H15) -> 8000000 | I16: =SUM(I14:I15) -> 8000000 | J16: =SUM(J14:J15) -> 1 | L16: =K14/($I$18) -> 0.2 | M16: Remaining Option Pool
L17: =SUM(L14:L16) -> 1
I18: =I16+K14 -> 10000000 | J18: Fully-Diluted Shares
B21: Post Series A Preferred Stock Fianncing
B22: Prior Conversion Price | C22: Adjusted Conversion Price | D22: Adjusted Conversion Ratio | E22: Shares Outstanding | F22: Options Outstanding | G22: Warrants Outstanding | H22: Total Outstanding | I22: Total Common Equiv. O/S | J22: Percentage | K22: Remaining Option Pool | L22: Fully Diluted Percentage
A23: Common | D23: 1 | E23: =E14 -> 7000000 | F23: =F14 -> 0 | G23: =G14 -> 0 | H23: =SUM(E23:G23) -> 7000000 | I23: =ROUND((H23*D23),0) -> 7000000 | J23: =I23/$I$26 -> 0.38159306 | K23: =K14+B28 -> 4586037 | L23: =I23/$I$28 -> 0.30527445
A24: Series FF Preferred Stock | B24: =C15 -> 0.01 | C24: =B24 -> 0.01 | D24: =B24/C24 -> 1 | E24: =E15 -> 1000000 | F24: 0 | G24: =G15 -> 0 | H24: =SUM(E24:G24) -> 1000000 | I24: =ROUND((H24*D24),0) -> 1000000 | J24: =I24/$I$26 -> 0.054513295 | L24: =I24/$I$28 -> 0.043610636
A25: Series A Preferred Stock | B25: =B5 -> 0.47671876 | C25: =B5 -> 0.47671876 | D25: =B25/C25 -> 1 | E25: =C33 -> 10344149 | F25: 0 | G25: 0 | H25: =SUM(E25:G25) -> 10344149 | I25: =ROUND((H25*D25),0) -> 10344149 | J25: =I25/$I$26 -> 0.56389364 | L25: =I25/$I$28 -> 0.45111492
A26: Total | E26: =SUM(E23:E25) -> 18344149 | F26: =SUM(F23:F25) -> 0 | G26: =SUM(G23:G25) -> 0 | H26: =SUM(H23:H25) -> 18344149 | I26: =SUM(I23:I25) -> 18344149 | J26: =SUM(J23:J25) -> 1 | L26: =K23/I28 -> 0.19999999 | M26: Remaining Option Pool
L27: =SUM(L23:L26) -> 1
A28: ISO Refresh with Series A Financing | B28: =IF(B9="n/a", 0, ROUND(((($I$26)*($B$9/(1-$B$9)))),0)-K14) -> 2586037 | I28: =I26+K23 -> 22930186 | J28: Fully-Diluted Shares
A30: Series A Investors | B30: Investment | C30: Sereis A Shares | D30: Series A (%) | E30: Fully Diluted (%)
A31: Investors | B31: =ROUNDUP((C31*$B$5),2) -> 3000000.2 | C31: ='Series A Preferred'!D3 -> 6293019 | D31: =C31/$C$33 -> 0.60836508 | E31: =C31/$I$28 -> 0.27444256
A32: Convertible Note Holders | C32: ='Convertible Notes'!G10 -> 4051130 | D32: =C32/$C$33 -> 0.39163492 | E32: =C32/$I$28 -> 0.17667236
B33: =SUM(B31:B31) -> 3000000.2 | C33: =SUM(C31:C32) -> 10344149 | D33: =SUM(D31:D32) -> 1 | E33: =SUM(E31:E32) -> 0.45111492
A38: A&R Charter | B38: ='FF Preferred'!B12 -> 1000000 | C38: Series FF Preferred
B39: =B38 -> 1000000 | C39: Common Shares for Preferred Conversion
B40: =H14 -> 7000000 | C40: Common Shares
B41: =K14 -> 2000000 | C41: Stock Plan
B42: =SUM(B38:B41) -> 11000000 | C42: total number of shares of all stock
B43: =B39+B40+B41 -> 10000000 | C43: total common stock
B44: =B38 -> 1000000 | C44: total preferred stock

Sheet Shareholder List
A1: Shareholder List
B2: Common | D2: FF Preferred | E2: Restricted | G2: Fully Diluted | H2: Fully Diluted Initial | J2: Series A | K2: Fully Diluted | L2: Fully Diluted
B3: Stock | D3: Stock | E3: Stock Grants | G3: Total Ownership | H3: Ownership Percentage | J3: Preferred | K3: Total Ownership | L3: Ownership Percentage
B4: ='Common Stock'!B6 -> 1590000 | C4: =B4/$B$14 -> 0.17666667 | D4: ='FF Preferred'!B11 -> 250000 | G4: =SUM(B4+D4+E4) -> 1840000 | H4: =G4/$G$14 -> 0.184 | K4: =G4 -> 1840000 | L4: =K4/$K$14 -> 0.0974625
B5: ='Common Stock'!B7 -> 1590000 | C5: =B5/$B$14 -> 0.17666667 | D5: ='FF Preferred'!B9 -> 250000 | G5: =SUM(B5+D5+E5) -> 1840000 | H5: =G5/$G$14 -> 0.184 | K5: =G5 -> 1840000 | L5: =K5/$K$14 -> 0.0974625
B6: ='Common Stock'!B8 -> 1590000 | C6: =B6/$B$14 -> 0.17666667 | D6: ='FF Preferred'!B10 -> 250000 | G6: =SUM(B6+D6+E6) -> 1840000 | H6: =G6/$G$14 -> 0.184 | K6: =G6 -> 1840000 | L6: =K6/$K$14 -> 0.0974625
B7: ='Common Stock'!B9 -> 1590000 | C7: =B7/$B$14 -> 0.17666667 | D7: ='FF Preferred'!B11 -> 250000 | G7: =SUM(B7+D7+E7) -> 1840000 | H7: =G7/$G$14 -> 0.184 | K7: =G7 -> 1840000 | L7: =K7/$K$14 -> 0.0974625
B8: ='Common Stock'!B10 -> 40000 | C8: =B8/$B$14 -> 0.0044444444 | G8: =SUM(B8+D8+E8) -> 40000 | H8: =G8/$G$14 -> 0.004 | K8: =G8 -> 40000 | L8: =K8/$K$14 -> 0.00211875
B9: ='Common Stock'!B11 -> 200000 | C9: =B9/$B$14 -> 0.022222222 | G9: =SUM(B9+D9+E9) -> 200000 | H9: =G9/$G$14 -> 0.02 | K9: =G9 -> 200000 | L9: =K9/$K$14 -> 0.01059375
B10: ='Common Stock'!B12 -> 200000 | C10: =B10/$B$14 -> 0.022222222 | G10: =SUM(B10+D10+E10) -> 200000 | H10: =G10/$G$14 -> 0.02 | K10: =G10 -> 200000 | L10: =K10/$K$14 -> 0.01059375
B11: ='Common Stock'!B13 -> 200000 | C11: =B11/$B$14 -> 0.022222222 | G11: =SUM(B11+D11+E11) -> 200000 | H11: =G11/$G$14 -> 0.02 | K11: =G11 -> 200000 | L11: =K11/$K$14 -> 0.01059375
A12: Options Available for Issuance | B12: ='2015 Option Plan'!B8 -> 2000000 | C12: =B12/$B$14 -> 0.22222222 | G12: =B12 -> 2000000 | H12: =G12/$G$14 -> 0.2 | J12: ='Summary Cap'!B28 -> 2586037 | K12: =J12+G12 -> 4586037 | L12: =K12/$K$14 -> 0.24291665
A13: Series A New Money Investors | G13: 0 | H13: =G13/G14 -> 0 | J13: ='Series A Preferred'!D4 -> 6293019 | K13: =J13 -> 6293019 | L13: =K13/$K$14 -> 0.33333335
B14: =SUM(B4:B12) -> 9000000 | C14: =SUM(C4:C12) -> 1 | D14: =SUM(D4:D7) -> 1000000 | E14: =SUM(E4:E12) -> 0 | G14: =B14+D14+E14 -> 10000000 | H14: =SUM(H4:H12) -> 1 | K14: =SUM(K4:K13) -> 18879056 | L14: =SUM(L4:L13) -> 1

Sheet Common Stock
A1: Common Stockholders--Current
A3: Common | B3: Outstanding
A4: Shareholders | B4: Common
A6: Shareholder 1 | B6: 1590000
A7: Shareholder 2 | B7: 1590000
A8: Shareholder 3 | B8: 1590000
A9: Shareholder 4 | B9: 1590000
A10: Shareholder 5 | B10: 40000
A11: Shareholder 6 | B11: 200000
A12: Shareholder 7 | B12: 200000
A13: Shareholder 8 | B13: 200000
B14: =SUM(B6:B13) -> 7000000
A17: Common Stockholders--Post Recapitalization
D19: Fully Diluted
A20: Common | B20: Outstanding | C20: Class | D20: Ownership with
A21: Shareholders | B21: Common Stock | C21: Ownership | D21: FF Preferred
A22: =A6 -> Shareholder 1 | B22: =B6 -> 1590000 | C22: =B22/$B$30 -> 0.22714286 | D22: =(B22+'FF Preferred'!B11)/'Summary Cap'!$I$18 -> 0.184
A23: =A7 -> Shareholder 2 | B23: =B7 -> 1590000 | C23: =B23/$B$30 -> 0.22714286 | D23: =(B23+'FF Preferred'!B12)/'Summary Cap'!$I$18 -> 0.259
A24: =A8 -> Shareholder 3 | B24: =B8 -> 1590000 | C24: =B24/$B$30 -> 0.22714286 | D24: =(B24+'FF Preferred'!B13)/'Summary Cap'!$I$18 -> 0.159
A25: =A9 -> Shareholder 4 | B25: =B9 -> 1590000 | C25: =B25/$B$30 -> 0.22714286 | D25: =(B25+'FF Preferred'!B14)/'Summary Cap'!$I$18 -> 0.159
A26: =A10 -> Shareholder 5 | B26: =B10 -> 40000 | C26: =B26/$B$30 -> 0.0057142857 | D26: =(B26+'FF Preferred'!B15)/'Summary Cap'!$I$18 -> 0.004
A27: =A11 -> Shareholder 6 | B27: =B11 -> 200000 | C27: =B27/$B$30 -> 0.028571429 | D27: =(B27+'FF Preferred'!B16)/'Summary Cap'!$I$18 -> 0.02
A28: =A12 -> Shareholder 7 | B28: =B12 -> 200000 | C28: =B28/$B$30 -> 0.028571429 | D28: =(B28+'FF Preferred'!B17)/'Summary Cap'!$I$18 -> 0.02
A29: =A13 -> Shareholder 8 | B29: =B13 -> 200000 | C29: =B29/$B$30 -> 0.028571429 | D29: =(B29)/'Summary Cap'!$I$18 -> 0.02
A30: Total Common Stock Issued | B30: =SUM(B22:B29) -> 7000000 | C30: =SUM(C22:C29) -> 1 | D30: =SUM(D22:D29) -> 0.825

Sheet FF Preferred
A1: Series FF Preferred Stockholders--Current
D5: Pre Series A
A6: FF Preferred | B6: Outstanding | C6: Class | D6: Fully Diluted
A7: Stockholders | B7: FF Preferred Stock | C7: Ownership | D7: Ownership
A8: Sharedholder 1 | B8: 250000
A9: Sharedholder 2 | B9: 250000
A10: Sharedholder 3 | B10: 250000
A11: Sharedholder 4 | B11: 250000 | C11: =B11/$B$12 -> 0.25 | D11: =B11/'Summary Cap'!$I$18 -> 0.025
A12: Total | B12: =SUM(B8:B11) -> 1000000 | C12: =SUM(C11:C11) -> 0.25 | D12: =SUM(D11:D11) -> 0.025

Sheet 2015 Option Plan
A1: Option Plan--Current
A3: Shares Reserved for Issuance | B3: 2000000
A4: Options Issued and Outstanding | B4: =B28 -> 0
A5: Options Exercised | B5: 0
A6: Restricted Stock Grants | B6: 0
A7: Options Returned to Plan | B7: 0
A8: Options Avaliable For Grant | B8: =B3-B4-B5-B6+B7 -> 2000000
A12: Post Series A Closing Option Numbers
A13: Shares Reserved for Issuance | B13: =B3+'Summary Cap'!B28 -> 4586037
A14: Options Issued and Outstanding | B14: 0
A15: Options Exercised | B15: =B5 -> 0
A16: Restricted Stock Grants | B16: =B6 -> 0
A17: Options Returned to Plan | B17: =B7 -> 0
A18: Options Avaliable For Grant | B18: =B13-B14-B15-B16+B17 -> 4586037

Sheet Convertible Notes
A1: Convertible Noteholders
A3: Conversion Date: | B3: 42551
A4: Interest Rate | B4: 0.03
A5: Fully Dilited Shares | B5: 9520000 | D5: Discount to Series A
A6: Conversion Price (i) | B6: ='Summary Cap'!B5*(1-'Convertible Notes'!D6) -> 0.38137501 | D6: 0.2
A8: Noteholders | B8: Principal | C8: Issuance Date | D8: Days Outstanding | E8: Accrued Interest | F8: Principal and Interest | G8: Series A Shares | H8: Cash Payment
A9: Convertible Note Holders | B9: 1500000 | C9: 42186 | D9: =$B$3-C9 -> 365 | E9: =ROUND((B9*$B$4*D9/365),2) -> 45000 | F9: =B9+E9 -> 1545000 | G9: =ROUNDDOWN((F9/$B$6),0) -> 4051130 | H9: =F9-(G9*$B$6) -> 0.25087734
B10: =SUM(B9:B9) -> 1500000 | E10: =SUM(E9:E9) -> 45000 | F10: =SUM(F9:F9) -> 1545000 | G10: =SUM(G9:G9) -> 4051130 | H10: =SUM(H9:H9) -> 0.25087734

Sheet Series A Preferred
A1: Series A Investor | B1: Investment | C1: Series A from Convertible Notes | D1: Total Series A | E1: Series A % | F1: Fully-Diluted %
A2: Lead Investors
A3: Investors | B3: ='Summary Cap'!B31 -> 3000000.2 | D3: =ROUNDUP((3000000/'Summary Cap'!$B$5),0) -> 6293019 | E3: =D3/'Summary Cap'!$C$33 -> 0.60836508 | F3: =D3/'Summary Cap'!$I$28 -> 0.27444256
A4: Total Series A Preferred Total | B4: =B3 -> 3000000.2 | D4: =D3 -> 6293019
A6: Total Preferred (FF Preferred + Series A) | D6: =D4+'FF Preferred'!B12 -> 7293019
